{
    "user1": {
        "image_path": "registered_images/luan.jpeg",
        "access_level": 1,
        "name": "Luan"
    },
    "user2": {
        "image_path": "registered_images/dell.jpeg",
        "access_level": 2,
        "name": "Dell"
    },
    "user3": {
        "image_path": "registered_images/leticia.jpeg",
        "access_level": 1,
        "name": "Leticia"
    },
    "user4": {
        "image_path": "registered_images/labrinth.jpeg",
        "access_level": 4,
        "name": "Labrinth"
    },
    "user5": {
        "image_path": "registered_images/gaules.jpeg",
        "access_level": 3,
        "name": "Gaules"
    }

}